search_prompts/__init__.py
search_prompts/main.py
search_prompts-1.3.0.dist-info/METADATA
search_prompts-1.3.0.dist-info/WHEEL
search_prompts-1.3.0.dist-info/top_level.txt
search_prompts-1.3.0.dist-info/RECORD
