Metadata-Version: 2.1
Name: search-prompts
Version: 1.3.0
Summary: A library for efficient text-based prompt search with resource monitoring.
Author: Kozlovskiy Sergei
Classifier: Programming Language :: Python :: 3
Classifier: License :: OSI Approved :: MIT License
Classifier: Operating System :: OS Independent
Requires-Python: >=3.7
Requires-Dist: psutil
Requires-Dist: memory-profiler
Requires-Dist: datasets
